setup.py
bi_gaus_dist_by_Lokendra/Binomialdistribution.py
bi_gaus_dist_by_Lokendra/Gaussiandistribution.py
bi_gaus_dist_by_Lokendra/Generaldistribution.py
bi_gaus_dist_by_Lokendra/__init__.py
bi_gaus_dist_by_Lokendra.egg-info/PKG-INFO
bi_gaus_dist_by_Lokendra.egg-info/SOURCES.txt
bi_gaus_dist_by_Lokendra.egg-info/dependency_links.txt
bi_gaus_dist_by_Lokendra.egg-info/not-zip-safe
bi_gaus_dist_by_Lokendra.egg-info/top_level.txt