Metadata-Version: 1.0
Name: bi-gaus-dist-by-Lokendra
Version: 0.3
Summary: Gaussian distribution and Binomial distribution
Home-page: UNKNOWN
Author: LokendraBhat
Author-email: UNKNOWN
License: UNKNOWN
Platform: UNKNOWN
